LICENSE.txt
MANIFEST.in
README.rst
requirements.txt
setup.py
ctmatching/__init__.py
ctmatching/core.py
ctmatching/dataset.py
ctmatching/exc.py
ctmatching/orderedset.py
ctmatching/zzz_manual_install.py
ctmatching.egg-info/PKG-INFO
ctmatching.egg-info/SOURCES.txt
ctmatching.egg-info/dependency_links.txt
ctmatching.egg-info/requires.txt
ctmatching.egg-info/top_level.txt
ctmatching/__pycache__/__init__.cpython-34.pyc
ctmatching/__pycache__/core.cpython-34.pyc
ctmatching/__pycache__/dataset.cpython-34.pyc
ctmatching/__pycache__/exc.cpython-34.pyc
ctmatching/__pycache__/orderedset.cpython-34.pyc
ctmatching/testdata/re78-readme.html
ctmatching/testdata/re78.txt